Metadata-Version: 2.4
Name: treesitter-mcp
Version: 2.1
Summary: MCP server for code analysis using Tree-sitter
Project-URL: Homepage, https://github.com/pwno-io/treesitter-mcp
Project-URL: Repository, https://github.com/pwno-io/treesitter-mcp
Project-URL: Issues, https://github.com/pwno-io/treesitter-mcp/issues
Author: pwno-io
Keywords: ast,cli,code-analysis,mcp,tree-sitter
Classifier: Development Status :: 3 - Alpha
Classifier: Environment :: Console
Classifier: Intended Audience :: Developers
Classifier: Programming Language :: Python :: 3
Classifier: Programming Language :: Python :: 3 :: Only
Classifier: Programming Language :: Python :: 3.10
Classifier: Topic :: Software Development :: Compilers
Classifier: Topic :: Software Development :: Libraries :: Python Modules
Requires-Python: >=3.10
Requires-Dist: mcp
Requires-Dist: orjson>=3.9.0
Requires-Dist: pydantic
Requires-Dist: tree-sitter-c
Requires-Dist: tree-sitter-cpp
Requires-Dist: tree-sitter-go
Requires-Dist: tree-sitter-java
Requires-Dist: tree-sitter-javascript
Requires-Dist: tree-sitter-php
Requires-Dist: tree-sitter-python
Requires-Dist: tree-sitter-ruby
Requires-Dist: tree-sitter-rust
Requires-Dist: tree-sitter-typescript
Requires-Dist: tree-sitter>=0.22.0
Provides-Extra: dev
Requires-Dist: pytest; extra == 'dev'
